records.py
records_csp-0.5.3.1.dist-info/LICENSE
records_csp-0.5.3.1.dist-info/METADATA
records_csp-0.5.3.1.dist-info/WHEEL
records_csp-0.5.3.1.dist-info/entry_points.txt
records_csp-0.5.3.1.dist-info/top_level.txt
records_csp-0.5.3.1.dist-info/RECORD
