Metadata-Version: 2.1
Name: records-csp
Version: 0.5.3.1
Summary: SQL for Humans
Home-page: https://github.com/kennethreitz/records
Author: Kenneth Reitz
Author-email: me@kennethreitz.org
License: ISC
Classifier: Development Status :: 5 - Production/Stable
Classifier: Intended Audience :: Developers
Classifier: Natural Language :: English
Classifier: License :: OSI Approved :: ISC License (ISCL)
Classifier: Programming Language :: Python
Classifier: Programming Language :: Python :: 2
Classifier: Programming Language :: Python :: 2.7
Classifier: Programming Language :: Python :: 3
Classifier: Programming Language :: Python :: 3.4
Classifier: Programming Language :: Python :: 3.5
Classifier: Programming Language :: Python :: 3.6
Classifier: Programming Language :: Python :: Implementation :: CPython
License-File: LICENSE
Requires-Dist: openpyxl (<2.5.0)
Requires-Dist: tablib (>=0.11.4)
Requires-Dist: docopt
Requires-Dist: SQLAlchemy (<1.1) ; python_version < "3.0"
Requires-Dist: SQLAlchemy ; python_version >= "3.0"
Provides-Extra: pandas
Requires-Dist: tablib[pandas] ; extra == 'pandas'
Provides-Extra: pg
Requires-Dist: psycopg2 ; extra == 'pg'
Provides-Extra: redshift
Requires-Dist: sqlalchemy-redshift ; extra == 'redshift'
Requires-Dist: psycopg2 ; extra == 'redshift'
